lab03/__init__.py
lab03/lab03.py
lab03-0.0.1.dist-info/METADATA
lab03-0.0.1.dist-info/WHEEL
lab03-0.0.1.dist-info/top_level.txt
lab03-0.0.1.dist-info/RECORD
