Metadata-Version: 2.1
Name: lab03
Version: 0.0.1
Summary: Lab 03 Package
Home-page: UNKNOWN
Author: Nicholas Carr
Author-email: ncarr@g.emporia.edu
License: UNKNOWN
Keywords: python,first package
Platform: UNKNOWN
Classifier: Development Status :: 3 - Alpha
Classifier: Intended Audience :: Education
Classifier: Programming Language :: Python :: 2
Classifier: Programming Language :: Python :: 3
Classifier: Operating System :: MacOS :: MacOS X
Classifier: Operating System :: Microsoft :: Windows
